README.txt
setup.py
savelist/__init__.py
savelist/savelist.py
savelist.egg-info/PKG-INFO
savelist.egg-info/SOURCES.txt
savelist.egg-info/dependency_links.txt
savelist.egg-info/top_level.txt
savelist.egg-info/zip-safe