Metadata-Version: 1.1
Name: savelist
Version: 1.0.1
Summary: this is a test package for packing python liberaries tutorial.
Home-page: https://github.com/BoKaiSun/savelist/tree/master
Author: sunbokai
Author-email: sunjunjerry@outlook.com
License: UNKNOWN
Keywords: test python package
Platform: UNKNOWN
Classifier: License :: OSI Approved :: MIT License
Classifier: Programming Language :: Python
Classifier: Intended Audience :: Developers
Classifier: Operating System :: OS Independent
